access/__init__.py
access/fca/__init__.py
access/fca/fca1.py
access/fca/fca2.py
access/fca/fca3.py
access/helpers/__init__.py
access/helpers/helpers.py
access/raam/__init__.py
access/raam/raam.py
access/tests/__init__.py
access/weights/__init__.py
access/weights/weights.py
access_jamessaxon-1.0.0.dist-info/LICENSE
access_jamessaxon-1.0.0.dist-info/METADATA
access_jamessaxon-1.0.0.dist-info/WHEEL
access_jamessaxon-1.0.0.dist-info/top_level.txt
access_jamessaxon-1.0.0.dist-info/RECORD
